dexpaprika_sdk/__init__.py
dexpaprika_sdk/client.py
dexpaprika_sdk/api/__init__.py
dexpaprika_sdk/api/base.py
dexpaprika_sdk/api/dexes.py
dexpaprika_sdk/api/networks.py
dexpaprika_sdk/api/pools.py
dexpaprika_sdk/api/search.py
dexpaprika_sdk/api/tokens.py
dexpaprika_sdk/api/utils.py
dexpaprika_sdk/models/__init__.py
dexpaprika_sdk/models/base.py
dexpaprika_sdk/models/networks.py
dexpaprika_sdk/models/pools.py
dexpaprika_sdk/models/search.py
dexpaprika_sdk/models/tokens.py
dexpaprika_sdk/models/utils.py
dexpaprika_sdk/utils/__init__.py
dexpaprika_sdk/utils/perf.py
dexpaprika_sdk-0.3.0.dist-info/METADATA
dexpaprika_sdk-0.3.0.dist-info/WHEEL
dexpaprika_sdk-0.3.0.dist-info/top_level.txt
dexpaprika_sdk-0.3.0.dist-info/RECORD
