Metadata-Version: 2.4
Name: dexpaprika-sdk
Version: 0.3.0
Summary: Python SDK for the DexPaprika API
Home-page: https://github.com/coinpaprika/dexpaprika-sdk-python
Author: CoinPaprika
Author-email: CoinPaprika <support@coinpaprika.com>
License: MIT
Project-URL: Homepage, https://github.com/coinpaprika/dexpaprika-sdk-python
Project-URL: Bug Tracker, https://github.com/coinpaprika/dexpaprika-sdk-python/issues
Project-URL: Documentation, https://docs.dexpaprika.com
Keywords: dexpaprika,crypto,blockchain,defi,api,sdk
Classifier: Development Status :: 4 - Beta
Classifier: Intended Audience :: Developers
Classifier: Programming Language :: Python :: 3
Classifier: Programming Language :: Python :: 3.8
Classifier: Programming Language :: Python :: 3.9
Classifier: Programming Language :: Python :: 3.10
Classifier: Programming Language :: Python :: 3.11
Classifier: Topic :: Software Development :: Libraries :: Python Modules
Classifier: Topic :: Software Development :: Libraries
Classifier: Topic :: Software Development
Classifier: Typing :: Typed
Requires-Python: >=3.8
Requires-Dist: requests>=2.25.0
Requires-Dist: pydantic>=2.0.0
Provides-Extra: dev
Requires-Dist: pytest>=7.0.0; extra == "dev"
Requires-Dist: pytest-cov>=4.0.0; extra == "dev"
Requires-Dist: black>=23.0.0; extra == "dev"
Requires-Dist: isort>=5.12.0; extra == "dev"
Requires-Dist: mypy>=1.0.0; extra == "dev"
Requires-Dist: twine>=4.0.0; extra == "dev"
Requires-Dist: build>=0.10.0; extra == "dev"
Dynamic: author
Dynamic: home-page
Dynamic: provides-extra
Dynamic: requires-python
